__init__.py
llmcodxtracter/__init__.py
llmcodxtracter/exceptions.py
llmcodxtracter/extractor.py
llmcodxtracter/processor.py
llmcodxtracter/validator.py
llmcodxtracter-0.2.5.dist-info/METADATA
llmcodxtracter-0.2.5.dist-info/WHEEL
llmcodxtracter-0.2.5.dist-info/top_level.txt
llmcodxtracter-0.2.5.dist-info/RECORD
