Metadata-Version: 2.2
Name: llmcodxtracter
Version: 0.2.5
Summary: A Python library for extracting code snippets using LLMs
Author-email: Mohammed Muzammil Inamdar <muzammil.inamdar98@gmail.com>
License: MIT
Project-URL: Homepage, https://github.com/DarthMuzammil/llmcodxtracter
Project-URL: Repository, https://github.com/DarthMuzammil/llmcodxtracter
Requires-Python: >=3.7
Requires-Dist: openai
